taler/__init__.py
taler/util/__init__.py
taler/util/amount.py
taler/util/gnunet_log.py
taler/util/payto.py
taler/util/taler_error_codes.py
taler/util/talerconfig.py
tests/__init__.py
tests/test_amount.py
tests/test_log.py
taler_util-0.8.3.dist-info/COPYING
taler_util-0.8.3.dist-info/METADATA
taler_util-0.8.3.dist-info/WHEEL
taler_util-0.8.3.dist-info/top_level.txt
taler_util-0.8.3.dist-info/RECORD
