Metadata-Version: 2.1
Name: taler-util
Version: 0.8.3
Summary: Util library for GNU Taler
Home-page: https://git.taler.net/taler-util.git
Author: Taler Systems SA
Author-email: ng0@taler.net
License: LGPL3+
Platform: any
Classifier: Programming Language :: Python :: 3 :: Only
Classifier: Programming Language :: Python :: 3
Classifier: Programming Language :: Python :: 3.7
Classifier: Programming Language :: Python :: 3.8
Classifier: License :: OSI Approved :: GNU Lesser General Public License v3 or later (LGPLv3+)
Classifier: Operating System :: OS Independent
Requires-Python: >=3.7
